tenduke_core/__init__.py
tenduke_core/auth/__init__.py
tenduke_core/auth/auth_provider.py
tenduke_core/auth/device_auth_response.py
tenduke_core/auth/device_flow_client.py
tenduke_core/auth/oauth_client.py
tenduke_core/auth/oidc_discovery.py
tenduke_core/auth/pkce_flow_client.py
tenduke_core/auth/token_response.py
tenduke_core/auth/user_info.py
tenduke_core/base_model.py
tenduke_core/config/__init__.py
tenduke_core/config/tenduke_config.py
tenduke_core/exceptions/__init__.py
tenduke_core/exceptions/api.py
tenduke_core/exceptions/oauth.py
tenduke_core/exceptions/validation.py
tenduke_core/http/__init__.py
tenduke_core/http/session_factory.py
tenduke_core/py.typed
tenduke_core-3.0.1.dist-info/LICENSE
tenduke_core-3.0.1.dist-info/METADATA
tenduke_core-3.0.1.dist-info/WHEEL
tenduke_core-3.0.1.dist-info/RECORD
